Workbook

Sheet Read Me
A1: FHC | Workbook Guide
A2: Purpose: management reporting and oversight; not a substitute for the official ledger or audited statements.
A4: 1. Reporting cycle | B4: Complete each business-unit sheet monthly; use consistent period cut-off and identify reporting currency.
A5: 2. Data quality | B5: Enter actual, source-supported figures. Blank means not provided; do not use zero to hide missing data.
A6: 3. Closing cash | B6: Calculated as opening cash + cash inflows - cash outflows. Reconcile against bank and cash records.
A7: 4. Group dashboard | B7: Pulls key figures from each unit sheet. Formula recalculation may occur when opened in Excel or LibreOffice.
A8: 5. Consolidation | B8: Group totals are management summaries. Assess intercompany transactions and eliminate duplicates where applicable.
A9: 6. KPI status | B9: Use Green/Amber/Red/Grey only against approved thresholds; Grey means missing or unvalidated data.
A10: 7. Confidentiality | B10: Do not store bank account numbers, passwords, KYC documents, investor personal data, or confidential contracts in a public repository.
A11: 8. Approval | B11: Prepared by, reviewed by, approval date, and evidence references should be completed under the company's control process.
A12: 9. Entity structure | B12: Confirm the legal entity represented by each unit before treating figures as statutory consolidated financial statements.
A15: Version | B15: 0.1 — Draft template
A16: Status | B16: For internal review; management approval required

Sheet Group Dashboard
A1: FHC | Group Finance & KPI Dashboard
A2: Management reporting template — enter verified figures in the business-unit sheets. Blank values are not treated as zero.
A4: Reporting Month | D4: Reporting Currency | E4: IDR (change if needed)
A6: Business Unit | B6: Revenue | C6: Cost of Sales | D6: Gross Profit | E6: Operating Expenses | F6: Net Profit / (Loss) | G6: Closing Cash | H6: KPI / Reporting Status
A7: DA-B | B7: =IF(COUNTIF('DA-B'!B8:B8,">=0")+COUNTIF('DA-B'!B8:B8,"<0")=0,"",'DA-B'!B8) | C7: =IF(COUNTIF('DA-B'!B9:B9,">=0")+COUNTIF('DA-B'!B9:B9,"<0")=0,"",'DA-B'!B9) | D7: =IF(OR(B7="",C7=""),"",B7-C7) | E7: =IF(COUNTIF('DA-B'!B10:B10,">=0")+COUNTIF('DA-B'!B10:B10,"<0")=0,"",'DA-B'!B10) | F7: =IF(OR(D7="",E7=""),"",D7-E7) | G7: =IF(COUNTIF('DA-B'!B13:B13,">=0")+COUNTIF('DA-B'!B13:B13,"<0")=0,"",'DA-B'!B13) | H7: =IF(COUNT('DA-B'!B7:B9)=0,"Awaiting data",IF('DA-B'!B21="","Review needed",'DA-B'!B21))
A8: DA-RS | B8: =IF(COUNTIF('DA-RS'!B8:B8,">=0")+COUNTIF('DA-RS'!B8:B8,"<0")=0,"",'DA-RS'!B8) | C8: =IF(COUNTIF('DA-RS'!B9:B9,">=0")+COUNTIF('DA-RS'!B9:B9,"<0")=0,"",'DA-RS'!B9) | D8: =IF(OR(B8="",C8=""),"",B8-C8) | E8: =IF(COUNTIF('DA-RS'!B10:B10,">=0")+COUNTIF('DA-RS'!B10:B10,"<0")=0,"",'DA-RS'!B10) | F8: =IF(OR(D8="",E8=""),"",D8-E8) | G8: =IF(COUNTIF('DA-RS'!B13:B13,">=0")+COUNTIF('DA-RS'!B13:B13,"<0")=0,"",'DA-RS'!B13) | H8: =IF(COUNT('DA-RS'!B7:B9)=0,"Awaiting data",IF('DA-RS'!B21="","Review needed",'DA-RS'!B21))
A9: DA-MI | B9: =IF(COUNTIF('DA-MI'!B8:B8,">=0")+COUNTIF('DA-MI'!B8:B8,"<0")=0,"",'DA-MI'!B8) | C9: =IF(COUNTIF('DA-MI'!B9:B9,">=0")+COUNTIF('DA-MI'!B9:B9,"<0")=0,"",'DA-MI'!B9) | D9: =IF(OR(B9="",C9=""),"",B9-C9) | E9: =IF(COUNTIF('DA-MI'!B10:B10,">=0")+COUNTIF('DA-MI'!B10:B10,"<0")=0,"",'DA-MI'!B10) | F9: =IF(OR(D9="",E9=""),"",D9-E9) | G9: =IF(COUNTIF('DA-MI'!B13:B13,">=0")+COUNTIF('DA-MI'!B13:B13,"<0")=0,"",'DA-MI'!B13) | H9: =IF(COUNT('DA-MI'!B7:B9)=0,"Awaiting data",IF('DA-MI'!B21="","Review needed",'DA-MI'!B21))
A10: DA-Food | B10: =IF(COUNTIF('DA-Food'!B8:B8,">=0")+COUNTIF('DA-Food'!B8:B8,"<0")=0,"",'DA-Food'!B8) | C10: =IF(COUNTIF('DA-Food'!B9:B9,">=0")+COUNTIF('DA-Food'!B9:B9,"<0")=0,"",'DA-Food'!B9) | D10: =IF(OR(B10="",C10=""),"",B10-C10) | E10: =IF(COUNTIF('DA-Food'!B10:B10,">=0")+COUNTIF('DA-Food'!B10:B10,"<0")=0,"",'DA-Food'!B10) | F10: =IF(OR(D10="",E10=""),"",D10-E10) | G10: =IF(COUNTIF('DA-Food'!B13:B13,">=0")+COUNTIF('DA-Food'!B13:B13,"<0")=0,"",'DA-Food'!B13) | H10: =IF(COUNT('DA-Food'!B7:B9)=0,"Awaiting data",IF('DA-Food'!B21="","Review needed",'DA-Food'!B21))
A11: HGA | B11: =IF(COUNTIF('HGA'!B8:B8,">=0")+COUNTIF('HGA'!B8:B8,"<0")=0,"",'HGA'!B8) | C11: =IF(COUNTIF('HGA'!B9:B9,">=0")+COUNTIF('HGA'!B9:B9,"<0")=0,"",'HGA'!B9) | D11: =IF(OR(B11="",C11=""),"",B11-C11) | E11: =IF(COUNTIF('HGA'!B10:B10,">=0")+COUNTIF('HGA'!B10:B10,"<0")=0,"",'HGA'!B10) | F11: =IF(OR(D11="",E11=""),"",D11-E11) | G11: =IF(COUNTIF('HGA'!B13:B13,">=0")+COUNTIF('HGA'!B13:B13,"<0")=0,"",'HGA'!B13) | H11: =IF(COUNT('HGA'!B7:B9)=0,"Awaiting data",IF('HGA'!B21="","Review needed",'HGA'!B21))
A12: Group Total (entered units) | B12: =IF(COUNT(B7:B11)=0,"",SUM(B7:B11)) | C12: =IF(COUNT(C7:C11)=0,"",SUM(C7:C11)) | D12: =IF(COUNT(D7:D11)=0,"",SUM(D7:D11)) | E12: =IF(COUNT(E7:E11)=0,"",SUM(E7:E11)) | F12: =IF(COUNT(F7:F11)=0,"",SUM(F7:F11)) | G12: =IF(COUNT(G7:G11)=0,"",SUM(G7:G11))
A14: Important control
A15: This workbook is a management template, not an accounting system. Validate all inputs against source records; confirm entity, period, currency, intercompany eliminations, and approvals before relying on consolidated totals.

Sheet DA-B
A1: DA-B | Monthly Finance Report
A2: Input sheet — enter actual figures only after checking source records. Do not enter sensitive account/KYC details.
A4: Reporting Month | D4: Currency | E4: IDR
A6: Financial Summary
A7: Revenue
A8: Cost of Sales
A9: Operating Expenses
A10: Opening Cash Balance
A11: Cash Inflows
A12: Cash Outflows
A13: Closing Cash Balance | B13: =IF(COUNT(B10:B12)=0,"",B10+B11-B12)
A14: Receivables Outstanding
A15: Payables Outstanding
A16: Approved Budget
A17: Actual Expenditure
A18: Budget Variance (Budget - Actual) | B18: =IF(OR(B16="",B17=""),"",B16-B17)
A19: KPI Target / Description
A20: KPI Actual / Result
A21: KPI Status (Green/Amber/Red/Grey)
A22: Variance Explanation / Risk
A23: Corrective Action
A24: Action Owner
A25: Due Date
A26: Prepared By
A27: Reviewed By
A28: Approval / Review Date

Sheet DA-RS
A1: DA-RS | Monthly Finance Report
A2: Input sheet — enter actual figures only after checking source records. Do not enter sensitive account/KYC details.
A4: Reporting Month | D4: Currency | E4: IDR
A6: Financial Summary
A7: Revenue
A8: Cost of Sales
A9: Operating Expenses
A10: Opening Cash Balance
A11: Cash Inflows
A12: Cash Outflows
A13: Closing Cash Balance | B13: =IF(COUNT(B10:B12)=0,"",B10+B11-B12)
A14: Receivables Outstanding
A15: Payables Outstanding
A16: Approved Budget
A17: Actual Expenditure
A18: Budget Variance (Budget - Actual) | B18: =IF(OR(B16="",B17=""),"",B16-B17)
A19: KPI Target / Description
A20: KPI Actual / Result
A21: KPI Status (Green/Amber/Red/Grey)
A22: Variance Explanation / Risk
A23: Corrective Action
A24: Action Owner
A25: Due Date
A26: Prepared By
A27: Reviewed By
A28: Approval / Review Date

Sheet DA-MI
A1: DA-MI | Monthly Finance Report
A2: Input sheet — enter actual figures only after checking source records. Do not enter sensitive account/KYC details.
A4: Reporting Month | D4: Currency | E4: IDR
A6: Financial Summary
A7: Revenue
A8: Cost of Sales
A9: Operating Expenses
A10: Opening Cash Balance
A11: Cash Inflows
A12: Cash Outflows
A13: Closing Cash Balance | B13: =IF(COUNT(B10:B12)=0,"",B10+B11-B12)
A14: Receivables Outstanding
A15: Payables Outstanding
A16: Approved Budget
A17: Actual Expenditure
A18: Budget Variance (Budget - Actual) | B18: =IF(OR(B16="",B17=""),"",B16-B17)
A19: KPI Target / Description
A20: KPI Actual / Result
A21: KPI Status (Green/Amber/Red/Grey)
A22: Variance Explanation / Risk
A23: Corrective Action
A24: Action Owner
A25: Due Date
A26: Prepared By
A27: Reviewed By
A28: Approval / Review Date

Sheet DA-Food
A1: DA-Food | Monthly Finance Report
A2: Input sheet — enter actual figures only after checking source records. Do not enter sensitive account/KYC details.
A4: Reporting Month | D4: Currency | E4: IDR
A6: Financial Summary
A7: Revenue
A8: Cost of Sales
A9: Operating Expenses
A10: Opening Cash Balance
A11: Cash Inflows
A12: Cash Outflows
A13: Closing Cash Balance | B13: =IF(COUNT(B10:B12)=0,"",B10+B11-B12)
A14: Receivables Outstanding
A15: Payables Outstanding
A16: Approved Budget
A17: Actual Expenditure
A18: Budget Variance (Budget - Actual) | B18: =IF(OR(B16="",B17=""),"",B16-B17)
A19: KPI Target / Description
A20: KPI Actual / Result
A21: KPI Status (Green/Amber/Red/Grey)
A22: Variance Explanation / Risk
A23: Corrective Action
A24: Action Owner
A25: Due Date
A26: Prepared By
A27: Reviewed By
A28: Approval / Review Date

Sheet HGA
A1: HGA | Monthly Finance Report
A2: Input sheet — enter actual figures only after checking source records. Do not enter sensitive account/KYC details.
A4: Reporting Month | D4: Currency | E4: IDR
A6: Financial Summary
A7: Revenue
A8: Cost of Sales
A9: Operating Expenses
A10: Opening Cash Balance
A11: Cash Inflows
A12: Cash Outflows
A13: Closing Cash Balance | B13: =IF(COUNT(B10:B12)=0,"",B10+B11-B12)
A14: Receivables Outstanding
A15: Payables Outstanding
A16: Approved Budget
A17: Actual Expenditure
A18: Budget Variance (Budget - Actual) | B18: =IF(OR(B16="",B17=""),"",B16-B17)
A19: KPI Target / Description
A20: KPI Actual / Result
A21: KPI Status (Green/Amber/Red/Grey)
A22: Variance Explanation / Risk
A23: Corrective Action
A24: Action Owner
A25: Due Date
A26: Prepared By
A27: Reviewed By
A28: Approval / Review Date

Sheet KPI Register
A1: FHC | KPI Register
A2: Record one KPI per row. Targets and thresholds must be approved by management.
A4: Business Unit | B4: KPI Category | C4: KPI Name | D4: Definition / Formula | E4: Target | F4: Actual | G4: Unit | H4: Status | I4: Owner | J4: Reporting Period | K4: Evidence / Source | L4: Corrective Action
