Workbook

Sheet Read Me
A1: FHC | Performance Management Workbook Guide
A2: Draft template for internal review — no actual financial data is pre-filled.
A4: Purpose | B4: Monthly unit reporting, KPI tracking, management review, and action follow-up.
A5: Unit sheets | B5: Enter verified data in DA-B, DA-RS, DA-MI, DA-Food, and HGA sheets. Confirm legal entities and scope with management.
A6: Group Dashboard | B6: Summarizes unit-sheet values for management. It is not automatically a statutory consolidated financial statement.
A7: KPI Dictionary | B7: Proposed KPI definitions; confirm owners, formulas, target direction, and thresholds before use.
A8: Management Review | B8: Use one row per decision/action. Track owner, due date, status, and closure evidence.
A9: Blank vs zero | B9: Blank means not provided; zero is a real numeric value. Never treat missing data as zero or Green.
A10: Cash control | B10: Closing cash is calculated as opening cash + inflows - outflows; reconcile to bank/cash records.
A11: Consolidation | B11: Confirm entity, reporting period, currency, accounting basis, and intercompany eliminations before relying on totals.
A12: Confidentiality | B12: Do not store credentials, bank account details, investor personal data, KYC files, or confidential contracts in a public repository.
A13: Approval | B13: Management approval is required for targets, KPI thresholds, reporting responsibilities, and escalation rules.
A15: Version | B15: 0.2 — Draft
A16: Status | B16: For management review; not yet an approved policy

Sheet Group Dashboard
A1: FHC | Group Performance Dashboard
A2: Blank management template. Enter verified data in unit sheets; missing data remains blank / Grey.
A4: Reporting Period | D4: Reporting Currency | E4: IDR (confirm per entity)
A6: Business Unit | B6: Revenue | C6: Cost of Sales | D6: Gross Profit | E6: Operating Expenses | F6: Net Profit / (Loss) | G6: Closing Cash | H6: Data / KPI Status
A7: DA-B | B7: =IF(COUNT('DA-B'!B7)=0,"",'DA-B'!B7) | C7: =IF(COUNT('DA-B'!B8)=0,"",'DA-B'!B8) | D7: =IF(OR(B7="",C7=""),"",B7-C7) | E7: =IF(COUNT('DA-B'!B9)=0,"",'DA-B'!B9) | F7: =IF(OR(D7="",E7=""),"",D7-E7) | G7: =IF(COUNT('DA-B'!B13)=0,"",'DA-B'!B13) | H7: =IF('DA-B'!B22="","Grey / review",'DA-B'!B22)
A8: DA-RS | B8: =IF(COUNT('DA-RS'!B7)=0,"",'DA-RS'!B7) | C8: =IF(COUNT('DA-RS'!B8)=0,"",'DA-RS'!B8) | D8: =IF(OR(B8="",C8=""),"",B8-C8) | E8: =IF(COUNT('DA-RS'!B9)=0,"",'DA-RS'!B9) | F8: =IF(OR(D8="",E8=""),"",D8-E8) | G8: =IF(COUNT('DA-RS'!B13)=0,"",'DA-RS'!B13) | H8: =IF('DA-RS'!B22="","Grey / review",'DA-RS'!B22)
A9: DA-MI | B9: =IF(COUNT('DA-MI'!B7)=0,"",'DA-MI'!B7) | C9: =IF(COUNT('DA-MI'!B8)=0,"",'DA-MI'!B8) | D9: =IF(OR(B9="",C9=""),"",B9-C9) | E9: =IF(COUNT('DA-MI'!B9)=0,"",'DA-MI'!B9) | F9: =IF(OR(D9="",E9=""),"",D9-E9) | G9: =IF(COUNT('DA-MI'!B13)=0,"",'DA-MI'!B13) | H9: =IF('DA-MI'!B22="","Grey / review",'DA-MI'!B22)
A10: DA-Food | B10: =IF(COUNT('DA-Food'!B7)=0,"",'DA-Food'!B7) | C10: =IF(COUNT('DA-Food'!B8)=0,"",'DA-Food'!B8) | D10: =IF(OR(B10="",C10=""),"",B10-C10) | E10: =IF(COUNT('DA-Food'!B9)=0,"",'DA-Food'!B9) | F10: =IF(OR(D10="",E10=""),"",D10-E10) | G10: =IF(COUNT('DA-Food'!B13)=0,"",'DA-Food'!B13) | H10: =IF('DA-Food'!B22="","Grey / review",'DA-Food'!B22)
A11: HGA | B11: =IF(COUNT('HGA'!B7)=0,"",'HGA'!B7) | C11: =IF(COUNT('HGA'!B8)=0,"",'HGA'!B8) | D11: =IF(OR(B11="",C11=""),"",B11-C11) | E11: =IF(COUNT('HGA'!B9)=0,"",'HGA'!B9) | F11: =IF(OR(D11="",E11=""),"",D11-E11) | G11: =IF(COUNT('HGA'!B13)=0,"",'HGA'!B13) | H11: =IF('HGA'!B22="","Grey / review",'HGA'!B22)
A12: Group total (management view) | B12: =IF(COUNT(B7:B11)=0,"",SUM(B7:B11)) | C12: =IF(COUNT(C7:C11)=0,"",SUM(C7:C11)) | D12: =IF(COUNT(D7:D11)=0,"",SUM(D7:D11)) | E12: =IF(COUNT(E7:E11)=0,"",SUM(E7:E11)) | F12: =IF(COUNT(F7:F11)=0,"",SUM(F7:F11)) | G12: =IF(COUNT(G7:G11)=0,"",SUM(G7:G11))
A14: Controls before use
A15: Confirm legal entity, period, currency, accounting basis, supporting evidence, and intercompany eliminations. Totals are not statutory consolidated statements until approved consolidation procedures are applied.

Sheet DA-B
A1: DA-B | Monthly Performance Input
A2: Use verified figures only. Blank = missing; Grey = not validated. Do not enter confidential account/KYC data.
A4: Reporting Period | D4: Currency | E4: IDR (confirm)
A6: Financial inputs
A7: Revenue
A8: Cost of Sales
A9: Operating Expenses
A10: Opening Cash Balance
A11: Cash Inflows
A12: Cash Outflows
A13: Closing Cash Balance | B13: =IF(COUNT(B10:B12)=0,"",B10+B11-B12)
A14: Receivables Outstanding
A15: Payables Outstanding
A16: Approved Budget
A17: Actual Expenditure
A18: Budget Variance (Budget - Actual) | B18: =IF(OR(B16="",B17=""),"",B16-B17)
A19: KPI / operational section
A20: Primary KPI Name
A21: Approved KPI Target
A22: KPI Status (Green/Amber/Red/Grey)
A23: Variance / explanation
A24: Corrective action
A25: Action owner
A26: Due date
A27: Prepared by
A28: Reviewed by
A29: Approval / review date

Sheet DA-RS
A1: DA-RS | Monthly Performance Input
A2: Use verified figures only. Blank = missing; Grey = not validated. Do not enter confidential account/KYC data.
A4: Reporting Period | D4: Currency | E4: IDR (confirm)
A6: Financial inputs
A7: Revenue
A8: Cost of Sales
A9: Operating Expenses
A10: Opening Cash Balance
A11: Cash Inflows
A12: Cash Outflows
A13: Closing Cash Balance | B13: =IF(COUNT(B10:B12)=0,"",B10+B11-B12)
A14: Receivables Outstanding
A15: Payables Outstanding
A16: Approved Budget
A17: Actual Expenditure
A18: Budget Variance (Budget - Actual) | B18: =IF(OR(B16="",B17=""),"",B16-B17)
A19: KPI / operational section
A20: Primary KPI Name
A21: Approved KPI Target
A22: KPI Status (Green/Amber/Red/Grey)
A23: Variance / explanation
A24: Corrective action
A25: Action owner
A26: Due date
A27: Prepared by
A28: Reviewed by
A29: Approval / review date

Sheet DA-MI
A1: DA-MI | Monthly Performance Input
A2: Use verified figures only. Blank = missing; Grey = not validated. Do not enter confidential account/KYC data.
A4: Reporting Period | D4: Currency | E4: IDR (confirm)
A6: Financial inputs
A7: Revenue
A8: Cost of Sales
A9: Operating Expenses
A10: Opening Cash Balance
A11: Cash Inflows
A12: Cash Outflows
A13: Closing Cash Balance | B13: =IF(COUNT(B10:B12)=0,"",B10+B11-B12)
A14: Receivables Outstanding
A15: Payables Outstanding
A16: Approved Budget
A17: Actual Expenditure
A18: Budget Variance (Budget - Actual) | B18: =IF(OR(B16="",B17=""),"",B16-B17)
A19: KPI / operational section
A20: Primary KPI Name
A21: Approved KPI Target
A22: KPI Status (Green/Amber/Red/Grey)
A23: Variance / explanation
A24: Corrective action
A25: Action owner
A26: Due date
A27: Prepared by
A28: Reviewed by
A29: Approval / review date

Sheet DA-Food
A1: DA-Food | Monthly Performance Input
A2: Use verified figures only. Blank = missing; Grey = not validated. Do not enter confidential account/KYC data.
A4: Reporting Period | D4: Currency | E4: IDR (confirm)
A6: Financial inputs
A7: Revenue
A8: Cost of Sales
A9: Operating Expenses
A10: Opening Cash Balance
A11: Cash Inflows
A12: Cash Outflows
A13: Closing Cash Balance | B13: =IF(COUNT(B10:B12)=0,"",B10+B11-B12)
A14: Receivables Outstanding
A15: Payables Outstanding
A16: Approved Budget
A17: Actual Expenditure
A18: Budget Variance (Budget - Actual) | B18: =IF(OR(B16="",B17=""),"",B16-B17)
A19: KPI / operational section
A20: Primary KPI Name
A21: Approved KPI Target
A22: KPI Status (Green/Amber/Red/Grey)
A23: Variance / explanation
A24: Corrective action
A25: Action owner
A26: Due date
A27: Prepared by
A28: Reviewed by
A29: Approval / review date

Sheet HGA
A1: HGA | Monthly Performance Input
A2: Use verified figures only. Blank = missing; Grey = not validated. Do not enter confidential account/KYC data.
A4: Reporting Period | D4: Currency | E4: IDR (confirm)
A6: Financial inputs
A7: Revenue
A8: Cost of Sales
A9: Operating Expenses
A10: Opening Cash Balance
A11: Cash Inflows
A12: Cash Outflows
A13: Closing Cash Balance | B13: =IF(COUNT(B10:B12)=0,"",B10+B11-B12)
A14: Receivables Outstanding
A15: Payables Outstanding
A16: Approved Budget
A17: Actual Expenditure
A18: Budget Variance (Budget - Actual) | B18: =IF(OR(B16="",B17=""),"",B16-B17)
A19: KPI / operational section
A20: Primary KPI Name
A21: Approved KPI Target
A22: KPI Status (Green/Amber/Red/Grey)
A23: Variance / explanation
A24: Corrective action
A25: Action owner
A26: Due date
A27: Prepared by
A28: Reviewed by
A29: Approval / review date

Sheet KPI Dictionary
A1: FHC | KPI Dictionary
A2: Draft list. Management must approve KPI owner, target, threshold, and evidence requirements.
A4: Category | B4: KPI Name | C4: Definition / Formula | D4: Frequency | E4: Proposed Owner | F4: Unit | G4: Target | H4: Evidence / Source
A5: Finance | B5: Revenue | C5: Recognized revenue for reporting period | D5: Monthly | E5: Unit Finance / Finance Division | F5: Currency | H5: Ledger, invoices
A6: Finance | B6: Gross Profit | C6: Revenue - Cost of Sales | D6: Monthly | E6: Finance Division | F6: Currency | H6: Trial balance
A7: Finance | B7: Gross Margin % | C7: Gross Profit / Revenue * 100; N/A if revenue is zero | D7: Monthly | E7: Finance Division | F7: % | H7: Verified financial statements
A8: Finance | B8: Operating Expense Variance | C8: Actual operating expense - approved budget | D8: Monthly | E8: Unit Head / Finance | F8: Currency | H8: Approved budget and ledger
A9: Finance | B9: Budget Utilization % | C9: Actual expenditure / approved budget * 100; N/A if budget is zero | D9: Monthly | E9: Finance Division | F9: % | H9: Budget and ledger
A10: Finance | B10: Closing Cash | C10: Reconciled cash and bank balances at period end | D10: Monthly | E10: Treasury / Finance | F10: Currency | H10: Bank reconciliation
A11: Finance | B11: Overdue Receivables | C11: Receivables past due at reporting cut-off | D11: Monthly | E11: Finance / Credit Control | F11: Currency | H11: Aging report
A12: Governance | B12: Reporting Timeliness | C12: Reports received on time / reports expected * 100 | D12: Monthly | E12: Group Oversight | F12: % | H12: Submission log
A13: Risk | B13: Open High Risks | C13: Count of open high/critical risks under approved methodology | D13: Monthly | E13: Risk Owner | F13: Count | H13: Risk register
A14: Risk | B14: Overdue Actions | C14: Count of corrective actions past due and not closed | D14: Monthly | E14: Action Owners | F14: Count | H14: Action tracker
A15: Investment | B15: Due Diligence Completion | C15: Completed required checks / total required checks * 100 | D15: Per investment | E15: Investment Team | F15: % | H15: Controlled checklist
A16: Projects | B16: Milestone Delivery | C16: Milestones delivered on time / milestones due * 100 | D16: Monthly | E16: Project Owner | F16: % | H16: Approved project plan

Sheet Management Review
A1: FHC | Management Review & Action Log
A2: Record decisions, owners, due dates, status, and closure evidence.
A4: Review Date | B4: Period | C4: Unit | D4: Issue / KPI | E4: Decision / Action | F4: Owner | G4: Due Date | H4: Status / Evidence
